{
  "description": "Full access to Application Design Center resources.",
  "etag": "AA==",
  "includedPermissions": [
    "apphub.serviceProjectAttachments.list",
    "designcenter.applicationTemplateRevisions.delete",
    "designcenter.applicationTemplateRevisions.get",
    "designcenter.applicationTemplateRevisions.list",
    "designcenter.applicationTemplates.create",
    "designcenter.applicationTemplates.delete",
    "designcenter.applicationTemplates.get",
    "designcenter.applicationTemplates.list",
    "designcenter.applicationTemplates.update",
    "designcenter.applications.create",
    "designcenter.applications.delete",
    "designcenter.applications.get",
    "designcenter.applications.list",
    "designcenter.applications.update",
    "designcenter.catalogTemplateRevisions.create",
    "designcenter.catalogTemplateRevisions.delete",
    "designcenter.catalogTemplateRevisions.get",
    "designcenter.catalogTemplateRevisions.list",
    "designcenter.catalogTemplates.create",
    "designcenter.catalogTemplates.delete",
    "designcenter.catalogTemplates.get",
    "designcenter.catalogTemplates.list",
    "designcenter.catalogTemplates.update",
    "designcenter.catalogs.create",
    "designcenter.catalogs.delete",
    "designcenter.catalogs.get",
    "designcenter.catalogs.list",
    "designcenter.catalogs.update",
    "designcenter.components.create",
    "designcenter.components.delete",
    "designcenter.components.get",
    "designcenter.components.list",
    "designcenter.components.update",
    "designcenter.connections.create",
    "designcenter.connections.delete",
    "designcenter.connections.get",
    "designcenter.connections.list",
    "designcenter.connections.update",
    "designcenter.locations.get",
    "designcenter.locations.list",
    "designcenter.operations.cancel",
    "designcenter.operations.delete",
    "designcenter.operations.get",
    "designcenter.operations.list",
    "designcenter.sharedTemplateRevisions.get",
    "designcenter.sharedTemplateRevisions.list",
    "designcenter.sharedTemplates.get",
    "designcenter.sharedTemplates.list",
    "designcenter.shares.create",
    "designcenter.shares.delete",
    "designcenter.shares.get",
    "designcenter.shares.list",
    "designcenter.spaces.create",
    "designcenter.spaces.delete",
    "designcenter.spaces.get",
    "designcenter.spaces.getIamPolicy",
    "designcenter.spaces.list",
    "designcenter.spaces.setIamPolicy",
    "designcenter.spaces.update",
    "monitoring.timeSeries.create",
    "orgpolicy.policy.get",
    "resourcemanager.projects.get",
    "resourcemanager.projects.list",
    "storage.folders.create",
    "storage.folders.delete",
    "storage.folders.get",
    "storage.folders.list",
    "storage.folders.rename",
    "storage.managedFolders.create",
    "storage.managedFolders.delete",
    "storage.managedFolders.get",
    "storage.managedFolders.list",
    "storage.multipartUploads.abort",
    "storage.multipartUploads.create",
    "storage.multipartUploads.list",
    "storage.multipartUploads.listParts",
    "storage.objects.create",
    "storage.objects.delete",
    "storage.objects.get",
    "storage.objects.list",
    "storage.objects.move",
    "storage.objects.restore",
    "storage.objects.update"
  ],
  "name": "roles/designcenter.admin",
  "stage": "BETA",
  "title": "Application Design Center Admin"
}
