{
  "description": "Access to Graph Intelligence features.",
  "etag": "AA==",
  "includedPermissions": [
    "monitoring.timeSeries.create",
    "spanner.databases.beginReadOnlyTransaction",
    "spanner.databases.get",
    "spanner.databases.getDdl",
    "spanner.databases.partitionQuery",
    "spanner.databases.partitionRead",
    "spanner.databases.read",
    "spanner.databases.runGraphAlgorithms",
    "spanner.databases.select",
    "spanner.databases.useDataBoost",
    "spanner.instancePartitions.get",
    "spanner.instances.get",
    "spanner.sessions.create",
    "spanner.sessions.delete",
    "spanner.sessions.get",
    "spanner.sessions.list"
  ],
  "name": "roles/spanner.graphIntelligenceUser",
  "stage": "GA",
  "title": "Cloud Spanner Database Graph Intelligence features user"
}
