{
  "description": "Access to create, read, update and delete objects and multipart uploads in GCS.",
  "etag": "AA==",
  "includedPermissions": [
    "orgpolicy.policy.get",
    "resourcemanager.projects.get",
    "resourcemanager.projects.list",
    "storage.folders.create",
    "storage.folders.delete",
    "storage.folders.get",
    "storage.folders.list",
    "storage.folders.rename",
    "storage.managedFolders.create",
    "storage.managedFolders.delete",
    "storage.managedFolders.get",
    "storage.managedFolders.list",
    "storage.multipartUploads.abort",
    "storage.multipartUploads.create",
    "storage.multipartUploads.list",
    "storage.multipartUploads.listParts",
    "storage.objects.create",
    "storage.objects.delete",
    "storage.objects.get",
    "storage.objects.list",
    "storage.objects.restore",
    "storage.objects.update"
  ],
  "name": "roles/storage.objectUser",
  "stage": "GA",
  "title": "Storage Object User"
}
