{"name": "AmazonRDSEnhancedMonitoringRole", "deprecated": false, "createdate": "2015-11-11T19:58:29Z", "updatedate": "2015-11-11T19:58:29+00:00", "version": "v1", "malformed": false, "unknown_actions": [], "access_levels": ["Write", "Read", "List"], "document": {"Version": "2012-10-17", "Statement": [{"Sid": "EnableCreationAndManagementOfRDSCloudwatchLogGroups", "Effect": "Allow", "Action": ["logs:CreateLogGroup", "logs:PutRetentionPolicy"], "Resource": ["arn:aws:logs:*:*:log-group:RDS*"]}, {"Sid": "EnableCreationAndManagementOfRDSCloudwatchLogStreams", "Effect": "Allow", "Action": ["logs:CreateLogStream", "logs:PutLogEvents", "logs:DescribeLogStreams", "logs:GetLogEvents"], "Resource": ["arn:aws:logs:*:*:log-group:RDS*:log-stream:*"]}]}, "effective_actions": [{"action": "logs:CreateLogGroup", "effective_action": "logs:CreateLogGroup", "access_levels": "Write", "condition": null}, {"action": "logs:PutRetentionPolicy", "effective_action": "logs:PutRetentionPolicy", "access_levels": "Write", "condition": null}, {"action": "logs:CreateLogStream", "effective_action": "logs:CreateLogStream", "access_levels": "Write", "condition": null}, {"action": "logs:PutLogEvents", "effective_action": "logs:PutLogEvents", "access_levels": "Write", "condition": null}, {"action": "logs:DescribeLogStreams", "effective_action": "logs:DescribeLogStreams", "access_levels": "List", "condition": null}, {"action": "logs:GetLogEvents", "effective_action": "logs:GetLogEvents", "access_levels": "Read", "condition": null}]}