{
  "access_levels": [
    "List",
    "Read",
    "Write"
  ],
  "arn": "arn:aws:iam::aws:policy/aws-service-role/AmazonChimeVoiceConnectorServiceLinkedRolePolicy",
  "createdate": "2023-03-23T19:39:40Z",
  "credentials_exposure": false,
  "deprecated": false,
  "document": {
    "Statement": [
      {
        "Action": [
          "chime:GetVoiceConnector*"
        ],
        "Effect": "Allow",
        "Resource": [
          "*"
        ]
      },
      {
        "Action": [
          "kinesisvideo:GetDataEndpoint",
          "kinesisvideo:PutMedia",
          "kinesisvideo:UpdateDataRetention",
          "kinesisvideo:DescribeStream",
          "kinesisvideo:CreateStream"
        ],
        "Effect": "Allow",
        "Resource": [
          "arn:aws:kinesisvideo:*:*:stream/ChimeVoiceConnector-*"
        ]
      },
      {
        "Action": [
          "kinesisvideo:ListStreams"
        ],
        "Effect": "Allow",
        "Resource": [
          "*"
        ]
      },
      {
        "Action": [
          "SNS:Publish"
        ],
        "Effect": "Allow",
        "Resource": [
          "arn:aws:sns:*:*:ChimeVoiceConnector-Streaming*"
        ]
      },
      {
        "Action": [
          "sqs:SendMessage"
        ],
        "Effect": "Allow",
        "Resource": [
          "arn:aws:sqs:*:*:ChimeVoiceConnector-Streaming*"
        ]
      },
      {
        "Action": [
          "polly:SynthesizeSpeech"
        ],
        "Effect": "Allow",
        "Resource": [
          "*"
        ]
      },
      {
        "Action": [
          "chime:CreateMediaInsightsPipeline"
        ],
        "Effect": "Allow",
        "Resource": [
          "*"
        ]
      }
    ],
    "Version": "2012-10-17"
  },
  "effective_actions": [
    {
      "access_level": "Read",
      "action": "chime:GetVoiceConnector*",
      "condition": null,
      "credentials_exposure": false,
      "effective_action": "chime:GetVoiceConnector",
      "privesc": false,
      "resource_exposure": false
    },
    {
      "access_level": "Read",
      "action": "chime:GetVoiceConnector*",
      "condition": null,
      "credentials_exposure": false,
      "effective_action": "chime:GetVoiceConnectorEmergencyCallingConfiguration",
      "privesc": false,
      "resource_exposure": false
    },
    {
      "access_level": "Read",
      "action": "chime:GetVoiceConnector*",
      "condition": null,
      "credentials_exposure": false,
      "effective_action": "chime:GetVoiceConnectorGroup",
      "privesc": false,
      "resource_exposure": false
    },
    {
      "access_level": "Read",
      "action": "chime:GetVoiceConnector*",
      "condition": null,
      "credentials_exposure": false,
      "effective_action": "chime:GetVoiceConnectorLoggingConfiguration",
      "privesc": false,
      "resource_exposure": false
    },
    {
      "access_level": "Read",
      "action": "chime:GetVoiceConnector*",
      "condition": null,
      "credentials_exposure": false,
      "effective_action": "chime:GetVoiceConnectorOrigination",
      "privesc": false,
      "resource_exposure": false
    },
    {
      "access_level": "Read",
      "action": "chime:GetVoiceConnector*",
      "condition": null,
      "credentials_exposure": false,
      "effective_action": "chime:GetVoiceConnectorProxy",
      "privesc": false,
      "resource_exposure": false
    },
    {
      "access_level": "Read",
      "action": "chime:GetVoiceConnector*",
      "condition": null,
      "credentials_exposure": false,
      "effective_action": "chime:GetVoiceConnectorStreamingConfiguration",
      "privesc": false,
      "resource_exposure": false
    },
    {
      "access_level": "Read",
      "action": "chime:GetVoiceConnector*",
      "condition": null,
      "credentials_exposure": false,
      "effective_action": "chime:GetVoiceConnectorTermination",
      "privesc": false,
      "resource_exposure": false
    },
    {
      "access_level": "Read",
      "action": "chime:GetVoiceConnector*",
      "condition": null,
      "credentials_exposure": false,
      "effective_action": "chime:GetVoiceConnectorTerminationHealth",
      "privesc": false,
      "resource_exposure": false
    },
    {
      "access_level": "Read",
      "action": "kinesisvideo:GetDataEndpoint",
      "condition": null,
      "credentials_exposure": false,
      "effective_action": "kinesisvideo:GetDataEndpoint",
      "privesc": false,
      "resource_exposure": false
    },
    {
      "access_level": "Write",
      "action": "kinesisvideo:PutMedia",
      "condition": null,
      "credentials_exposure": false,
      "effective_action": "kinesisvideo:PutMedia",
      "privesc": false,
      "resource_exposure": false
    },
    {
      "access_level": "Write",
      "action": "kinesisvideo:UpdateDataRetention",
      "condition": null,
      "credentials_exposure": false,
      "effective_action": "kinesisvideo:UpdateDataRetention",
      "privesc": false,
      "resource_exposure": false
    },
    {
      "access_level": "List",
      "action": "kinesisvideo:DescribeStream",
      "condition": null,
      "credentials_exposure": false,
      "effective_action": "kinesisvideo:DescribeStream",
      "privesc": false,
      "resource_exposure": false
    },
    {
      "access_level": "Write",
      "action": "kinesisvideo:CreateStream",
      "condition": null,
      "credentials_exposure": false,
      "effective_action": "kinesisvideo:CreateStream",
      "privesc": false,
      "resource_exposure": false
    },
    {
      "access_level": "List",
      "action": "kinesisvideo:ListStreams",
      "condition": null,
      "credentials_exposure": false,
      "effective_action": "kinesisvideo:ListStreams",
      "privesc": false,
      "resource_exposure": false
    },
    {
      "access_level": "Write",
      "action": "SNS:Publish",
      "condition": null,
      "credentials_exposure": false,
      "effective_action": "sns:Publish",
      "privesc": false,
      "resource_exposure": false
    },
    {
      "access_level": "Write",
      "action": "sqs:SendMessage",
      "condition": null,
      "credentials_exposure": false,
      "effective_action": "sqs:SendMessage",
      "privesc": false,
      "resource_exposure": false
    },
    {
      "access_level": "Read",
      "action": "polly:SynthesizeSpeech",
      "condition": null,
      "credentials_exposure": false,
      "effective_action": "polly:SynthesizeSpeech",
      "privesc": false,
      "resource_exposure": false
    }
  ],
  "malformed": false,
  "name": "AmazonChimeVoiceConnectorServiceLinkedRolePolicy",
  "privesc": false,
  "resource_exposure": false,
  "undocumented_actions": false,
  "unknown_actions": [
    {
      "action": "chime:CreateMediaInsightsPipeline",
      "condition": null
    }
  ],
  "updatedate": "2023-03-23T19:39:40+00:00",
  "version": "v4"
}