{"name": "AWSCertificateManagerPrivateCAAuditor", "deprecated": false, "createdate": "2020-08-17T22:54:12Z", "updatedate": "2020-08-17T22:54:12+00:00", "version": "v4", "malformed": false, "unknown_actions": [], "access_levels": ["List", "Read", "Write"], "document": {"Version": "2012-10-17", "Statement": [{"Effect": "Allow", "Action": ["acm-pca:CreateCertificateAuthorityAuditReport", "acm-pca:DescribeCertificateAuthority", "acm-pca:DescribeCertificateAuthorityAuditReport", "acm-pca:GetCertificateAuthorityCsr", "acm-pca:GetCertificateAuthorityCertificate", "acm-pca:GetCertificate", "acm-pca:GetPolicy", "acm-pca:ListPermissions", "acm-pca:ListTags"], "Resource": "arn:aws:acm-pca:*:*:certificate-authority/*"}, {"Effect": "Allow", "Action": ["acm-pca:ListCertificateAuthorities"], "Resource": "*"}]}, "effective_actions": [{"action": "acm-pca:CreateCertificateAuthorityAuditReport", "effective_action": "acm-pca:CreateCertificateAuthorityAuditReport", "access_level": "Write", "condition": null}, {"action": "acm-pca:DescribeCertificateAuthority", "effective_action": "acm-pca:DescribeCertificateAuthority", "access_level": "Read", "condition": null}, {"action": "acm-pca:DescribeCertificateAuthorityAuditReport", "effective_action": "acm-pca:DescribeCertificateAuthorityAuditReport", "access_level": "Read", "condition": null}, {"action": "acm-pca:GetCertificateAuthorityCsr", "effective_action": "acm-pca:GetCertificateAuthorityCsr", "access_level": "Read", "condition": null}, {"action": "acm-pca:GetCertificateAuthorityCertificate", "effective_action": "acm-pca:GetCertificateAuthorityCertificate", "access_level": "Read", "condition": null}, {"action": "acm-pca:GetCertificate", "effective_action": "acm-pca:GetCertificate", "access_level": "Read", "condition": null}, {"action": "acm-pca:GetPolicy", "effective_action": "acm-pca:GetPolicy", "access_level": "Read", "condition": null}, {"action": "acm-pca:ListPermissions", "effective_action": "acm-pca:ListPermissions", "access_level": "Read", "condition": null}, {"action": "acm-pca:ListTags", "effective_action": "acm-pca:ListTags", "access_level": "Read", "condition": null}, {"action": "acm-pca:ListCertificateAuthorities", "effective_action": "acm-pca:ListCertificateAuthorities", "access_level": "List", "condition": null}]}