{
  "access_levels": [],
  "arn": "arn:aws:iam::aws:policy/aws-service-role/AccessAnalyzerServiceRolePolicy",
  "createdate": "2024-05-30T18:34:54+00:00",
  "credentials_exposure": false,
  "data_access": false,
  "deprecated": false,
  "document": {
    "Statement": [
      {
        "Action": [
          "dynamodb:GetResourcePolicy",
          "dynamodb:ListStreams",
          "dynamodb:ListTables",
          "ec2:DescribeAddresses",
          "ec2:DescribeByoipCidrs",
          "ec2:DescribeSnapshotAttribute",
          "ec2:DescribeSnapshots",
          "ec2:DescribeVpcEndpoints",
          "ec2:DescribeVpcs",
          "ec2:GetSnapshotBlockPublicAccessState",
          "ecr:DescribeRepositories",
          "ecr:GetRepositoryPolicy",
          "elasticfilesystem:DescribeFileSystemPolicy",
          "elasticfilesystem:DescribeFileSystems",
          "iam:GetRole",
          "iam:ListEntitiesForPolicy",
          "iam:ListRoles",
          "iam:ListUsers",
          "iam:GetUser",
          "iam:GetGroup",
          "iam:GenerateServiceLastAccessedDetails",
          "iam:GetServiceLastAccessedDetails",
          "iam:ListAccessKeys",
          "iam:GetLoginProfile",
          "iam:GetAccessKeyLastUsed",
          "iam:ListRolePolicies",
          "iam:GetRolePolicy",
          "iam:ListAttachedRolePolicies",
          "iam:ListUserPolicies",
          "iam:GetUserPolicy",
          "iam:ListAttachedUserPolicies",
          "iam:GetPolicy",
          "iam:GetPolicyVersion",
          "iam:ListGroupsForUser",
          "kms:DescribeKey",
          "kms:GetKeyPolicy",
          "kms:ListGrants",
          "kms:ListKeyPolicies",
          "kms:ListKeys",
          "lambda:GetFunctionUrlConfig",
          "lambda:GetLayerVersionPolicy",
          "lambda:GetPolicy",
          "lambda:ListAliases",
          "lambda:ListFunctions",
          "lambda:ListLayers",
          "lambda:ListLayerVersions",
          "lambda:ListVersionsByFunction",
          "organizations:DescribeAccount",
          "organizations:DescribeOrganization",
          "organizations:DescribeOrganizationalUnit",
          "organizations:ListAccounts",
          "organizations:ListAccountsForParent",
          "organizations:ListAWSServiceAccessForOrganization",
          "organizations:ListChildren",
          "organizations:ListDelegatedAdministrators",
          "organizations:ListOrganizationalUnitsForParent",
          "organizations:ListParents",
          "organizations:ListRoots",
          "rds:DescribeDBClusterSnapshotAttributes",
          "rds:DescribeDBClusterSnapshots",
          "rds:DescribeDBSnapshotAttributes",
          "rds:DescribeDBSnapshots",
          "s3:DescribeMultiRegionAccessPointOperation",
          "s3:GetAccessPoint",
          "s3:GetAccessPointPolicy",
          "s3:GetAccessPointPolicyStatus",
          "s3:GetAccountPublicAccessBlock",
          "s3:GetBucketAcl",
          "s3:GetBucketLocation",
          "s3:GetBucketPolicyStatus",
          "s3:GetBucketPolicy",
          "s3:GetBucketPublicAccessBlock",
          "s3:GetMultiRegionAccessPoint",
          "s3:GetMultiRegionAccessPointPolicy",
          "s3:GetMultiRegionAccessPointPolicyStatus",
          "s3:ListAccessPoints",
          "s3:ListAllMyBuckets",
          "s3:ListMultiRegionAccessPoints",
          "s3express:GetBucketPolicy",
          "s3express:ListAllMyDirectoryBuckets",
          "sns:GetTopicAttributes",
          "sns:ListTopics",
          "secretsmanager:DescribeSecret",
          "secretsmanager:GetResourcePolicy",
          "secretsmanager:ListSecrets",
          "sqs:GetQueueAttributes",
          "sqs:ListQueues"
        ],
        "Effect": "Allow",
        "Resource": "*",
        "Sid": "AccessAnalyzerServiceRolePolicy"
      }
    ],
    "Version": "2012-10-17"
  },
  "effective_actions": [],
  "malformed": false,
  "name": "AccessAnalyzerServiceRolePolicy",
  "privesc": false,
  "resource_exposure": false,
  "undocumented_actions": false,
  "unknown_actions": [
    {
      "action": "dynamodb:GetResourcePolicy",
      "condition": null
    },
    {
      "action": "dynamodb:ListStreams",
      "condition": null
    },
    {
      "action": "dynamodb:ListTables",
      "condition": null
    },
    {
      "action": "ec2:DescribeAddresses",
      "condition": null
    },
    {
      "action": "ec2:DescribeByoipCidrs",
      "condition": null
    },
    {
      "action": "ec2:DescribeSnapshotAttribute",
      "condition": null
    },
    {
      "action": "ec2:DescribeSnapshots",
      "condition": null
    },
    {
      "action": "ec2:DescribeVpcEndpoints",
      "condition": null
    },
    {
      "action": "ec2:DescribeVpcs",
      "condition": null
    },
    {
      "action": "ec2:GetSnapshotBlockPublicAccessState",
      "condition": null
    },
    {
      "action": "ecr:DescribeRepositories",
      "condition": null
    },
    {
      "action": "ecr:GetRepositoryPolicy",
      "condition": null
    },
    {
      "action": "elasticfilesystem:DescribeFileSystemPolicy",
      "condition": null
    },
    {
      "action": "elasticfilesystem:DescribeFileSystems",
      "condition": null
    },
    {
      "action": "iam:GetRole",
      "condition": null
    },
    {
      "action": "iam:ListEntitiesForPolicy",
      "condition": null
    },
    {
      "action": "iam:ListRoles",
      "condition": null
    },
    {
      "action": "iam:ListUsers",
      "condition": null
    },
    {
      "action": "iam:GetUser",
      "condition": null
    },
    {
      "action": "iam:GetGroup",
      "condition": null
    },
    {
      "action": "iam:GenerateServiceLastAccessedDetails",
      "condition": null
    },
    {
      "action": "iam:GetServiceLastAccessedDetails",
      "condition": null
    },
    {
      "action": "iam:ListAccessKeys",
      "condition": null
    },
    {
      "action": "iam:GetLoginProfile",
      "condition": null
    },
    {
      "action": "iam:GetAccessKeyLastUsed",
      "condition": null
    },
    {
      "action": "iam:ListRolePolicies",
      "condition": null
    },
    {
      "action": "iam:GetRolePolicy",
      "condition": null
    },
    {
      "action": "iam:ListAttachedRolePolicies",
      "condition": null
    },
    {
      "action": "iam:ListUserPolicies",
      "condition": null
    },
    {
      "action": "iam:GetUserPolicy",
      "condition": null
    },
    {
      "action": "iam:ListAttachedUserPolicies",
      "condition": null
    },
    {
      "action": "iam:GetPolicy",
      "condition": null
    },
    {
      "action": "iam:GetPolicyVersion",
      "condition": null
    },
    {
      "action": "iam:ListGroupsForUser",
      "condition": null
    },
    {
      "action": "kms:DescribeKey",
      "condition": null
    },
    {
      "action": "kms:GetKeyPolicy",
      "condition": null
    },
    {
      "action": "kms:ListGrants",
      "condition": null
    },
    {
      "action": "kms:ListKeyPolicies",
      "condition": null
    },
    {
      "action": "kms:ListKeys",
      "condition": null
    },
    {
      "action": "lambda:GetFunctionUrlConfig",
      "condition": null
    },
    {
      "action": "lambda:GetLayerVersionPolicy",
      "condition": null
    },
    {
      "action": "lambda:GetPolicy",
      "condition": null
    },
    {
      "action": "lambda:ListAliases",
      "condition": null
    },
    {
      "action": "lambda:ListFunctions",
      "condition": null
    },
    {
      "action": "lambda:ListLayers",
      "condition": null
    },
    {
      "action": "lambda:ListLayerVersions",
      "condition": null
    },
    {
      "action": "lambda:ListVersionsByFunction",
      "condition": null
    },
    {
      "action": "organizations:DescribeAccount",
      "condition": null
    },
    {
      "action": "organizations:DescribeOrganization",
      "condition": null
    },
    {
      "action": "organizations:DescribeOrganizationalUnit",
      "condition": null
    },
    {
      "action": "organizations:ListAccounts",
      "condition": null
    },
    {
      "action": "organizations:ListAccountsForParent",
      "condition": null
    },
    {
      "action": "organizations:ListAWSServiceAccessForOrganization",
      "condition": null
    },
    {
      "action": "organizations:ListChildren",
      "condition": null
    },
    {
      "action": "organizations:ListDelegatedAdministrators",
      "condition": null
    },
    {
      "action": "organizations:ListOrganizationalUnitsForParent",
      "condition": null
    },
    {
      "action": "organizations:ListParents",
      "condition": null
    },
    {
      "action": "organizations:ListRoots",
      "condition": null
    },
    {
      "action": "rds:DescribeDBClusterSnapshotAttributes",
      "condition": null
    },
    {
      "action": "rds:DescribeDBClusterSnapshots",
      "condition": null
    },
    {
      "action": "rds:DescribeDBSnapshotAttributes",
      "condition": null
    },
    {
      "action": "rds:DescribeDBSnapshots",
      "condition": null
    },
    {
      "action": "s3:DescribeMultiRegionAccessPointOperation",
      "condition": null
    },
    {
      "action": "s3:GetAccessPoint",
      "condition": null
    },
    {
      "action": "s3:GetAccessPointPolicy",
      "condition": null
    },
    {
      "action": "s3:GetAccessPointPolicyStatus",
      "condition": null
    },
    {
      "action": "s3:GetAccountPublicAccessBlock",
      "condition": null
    },
    {
      "action": "s3:GetBucketAcl",
      "condition": null
    },
    {
      "action": "s3:GetBucketLocation",
      "condition": null
    },
    {
      "action": "s3:GetBucketPolicyStatus",
      "condition": null
    },
    {
      "action": "s3:GetBucketPolicy",
      "condition": null
    },
    {
      "action": "s3:GetBucketPublicAccessBlock",
      "condition": null
    },
    {
      "action": "s3:GetMultiRegionAccessPoint",
      "condition": null
    },
    {
      "action": "s3:GetMultiRegionAccessPointPolicy",
      "condition": null
    },
    {
      "action": "s3:GetMultiRegionAccessPointPolicyStatus",
      "condition": null
    },
    {
      "action": "s3:ListAccessPoints",
      "condition": null
    },
    {
      "action": "s3:ListAllMyBuckets",
      "condition": null
    },
    {
      "action": "s3:ListMultiRegionAccessPoints",
      "condition": null
    },
    {
      "action": "s3express:GetBucketPolicy",
      "condition": null
    },
    {
      "action": "s3express:ListAllMyDirectoryBuckets",
      "condition": null
    },
    {
      "action": "sns:GetTopicAttributes",
      "condition": null
    },
    {
      "action": "sns:ListTopics",
      "condition": null
    },
    {
      "action": "secretsmanager:DescribeSecret",
      "condition": null
    },
    {
      "action": "secretsmanager:GetResourcePolicy",
      "condition": null
    },
    {
      "action": "secretsmanager:ListSecrets",
      "condition": null
    },
    {
      "action": "sqs:GetQueueAttributes",
      "condition": null
    },
    {
      "action": "sqs:ListQueues",
      "condition": null
    }
  ],
  "updatedate": "2024-05-30T18:34:54+00:00",
  "version": "v13"
}