{
  "access_levels": [
    "Read"
  ],
  "arn": "arn:aws:iam::aws:policy/AmazonSQSReadOnlyAccess",
  "createdate": "2024-05-24T18:16:44Z",
  "credentials_exposure": false,
  "data_access": false,
  "deprecated": false,
  "document": {
    "Statement": [
      {
        "Action": [
          "sqs:GetQueueAttributes",
          "sqs:GetQueueUrl",
          "sqs:ListDeadLetterSourceQueues",
          "sqs:ListQueues",
          "sqs:ListMessageMoveTasks",
          "sqs:ListQueueTags"
        ],
        "Effect": "Allow",
        "Resource": "*",
        "Sid": "AmazonSQSReadOnlyAccess"
      }
    ],
    "Version": "2012-10-17"
  },
  "effective_actions": [
    {
      "access_level": "Read",
      "action": "sqs:GetQueueAttributes",
      "condition": null,
      "credentials_exposure": false,
      "data_access": false,
      "effective_action": "sqs:GetQueueAttributes",
      "privesc": false,
      "resource_exposure": false
    },
    {
      "access_level": "Read",
      "action": "sqs:GetQueueUrl",
      "condition": null,
      "credentials_exposure": false,
      "data_access": false,
      "effective_action": "sqs:GetQueueUrl",
      "privesc": false,
      "resource_exposure": false
    },
    {
      "access_level": "Read",
      "action": "sqs:ListDeadLetterSourceQueues",
      "condition": null,
      "credentials_exposure": false,
      "data_access": false,
      "effective_action": "sqs:ListDeadLetterSourceQueues",
      "privesc": false,
      "resource_exposure": false
    },
    {
      "access_level": "Read",
      "action": "sqs:ListQueues",
      "condition": null,
      "credentials_exposure": false,
      "data_access": false,
      "effective_action": "sqs:ListQueues",
      "privesc": false,
      "resource_exposure": false
    },
    {
      "access_level": "Read",
      "action": "sqs:ListMessageMoveTasks",
      "condition": null,
      "credentials_exposure": false,
      "data_access": false,
      "effective_action": "sqs:ListMessageMoveTasks",
      "privesc": false,
      "resource_exposure": false
    },
    {
      "access_level": "Read",
      "action": "sqs:ListQueueTags",
      "condition": null,
      "credentials_exposure": false,
      "data_access": false,
      "effective_action": "sqs:ListQueueTags",
      "privesc": false,
      "resource_exposure": false
    }
  ],
  "malformed": false,
  "name": "AmazonSQSReadOnlyAccess",
  "privesc": false,
  "resource_exposure": false,
  "undocumented_actions": false,
  "unknown_actions": [],
  "updatedate": "2024-05-24T18:16:44+00:00",
  "version": "v4"
}