{
  "access_levels": [
    "List",
    "Read",
    "Tagging",
    "Write",
    "Permissions management"
  ],
  "arn": "arn:aws:iam::aws:policy/AmazonQLDBConsoleFullAccess",
  "createdate": "2022-11-04T17:01:10Z",
  "credentials_exposure": false,
  "data_access": true,
  "deprecated": false,
  "document": {
    "Statement": [
      {
        "Action": [
          "qldb:CreateLedger",
          "qldb:UpdateLedger",
          "qldb:UpdateLedgerPermissionsMode",
          "qldb:DeleteLedger",
          "qldb:ListLedgers",
          "qldb:DescribeLedger",
          "qldb:ExportJournalToS3",
          "qldb:ListJournalS3Exports",
          "qldb:ListJournalS3ExportsForLedger",
          "qldb:DescribeJournalS3Export",
          "qldb:CancelJournalKinesisStream",
          "qldb:DescribeJournalKinesisStream",
          "qldb:ListJournalKinesisStreamsForLedger",
          "qldb:StreamJournalToKinesis",
          "qldb:GetBlock",
          "qldb:GetDigest",
          "qldb:GetRevision",
          "qldb:TagResource",
          "qldb:UntagResource",
          "qldb:ListTagsForResource",
          "qldb:SendCommand",
          "qldb:ExecuteStatement",
          "qldb:ShowCatalog",
          "qldb:InsertSampleData",
          "qldb:PartiQLCreateTable",
          "qldb:PartiQLCreateIndex",
          "qldb:PartiQLDropTable",
          "qldb:PartiQLDropIndex",
          "qldb:PartiQLUndropTable",
          "qldb:PartiQLDelete",
          "qldb:PartiQLInsert",
          "qldb:PartiQLUpdate",
          "qldb:PartiQLSelect",
          "qldb:PartiQLHistoryFunction",
          "qldb:PartiQLRedact"
        ],
        "Effect": "Allow",
        "Resource": "*"
      },
      {
        "Action": [
          "dbqms:*"
        ],
        "Effect": "Allow",
        "Resource": "*"
      },
      {
        "Action": [
          "kinesis:ListStreams",
          "kinesis:DescribeStream"
        ],
        "Effect": "Allow",
        "Resource": "*"
      },
      {
        "Action": [
          "iam:PassRole"
        ],
        "Condition": {
          "StringEquals": {
            "iam:PassedToService": "qldb.amazonaws.com"
          }
        },
        "Effect": "Allow",
        "Resource": "*"
      }
    ],
    "Version": "2012-10-17"
  },
  "effective_actions": [
    {
      "access_level": "Write",
      "action": "qldb:CreateLedger",
      "condition": null,
      "credentials_exposure": false,
      "data_access": false,
      "effective_action": "qldb:CreateLedger",
      "privesc": false,
      "resource_exposure": false
    },
    {
      "access_level": "Write",
      "action": "qldb:UpdateLedger",
      "condition": null,
      "credentials_exposure": false,
      "data_access": false,
      "effective_action": "qldb:UpdateLedger",
      "privesc": false,
      "resource_exposure": false
    },
    {
      "access_level": "Write",
      "action": "qldb:UpdateLedgerPermissionsMode",
      "condition": null,
      "credentials_exposure": false,
      "data_access": false,
      "effective_action": "qldb:UpdateLedgerPermissionsMode",
      "privesc": false,
      "resource_exposure": false
    },
    {
      "access_level": "Write",
      "action": "qldb:DeleteLedger",
      "condition": null,
      "credentials_exposure": false,
      "data_access": false,
      "effective_action": "qldb:DeleteLedger",
      "privesc": false,
      "resource_exposure": false
    },
    {
      "access_level": "List",
      "action": "qldb:ListLedgers",
      "condition": null,
      "credentials_exposure": false,
      "data_access": false,
      "effective_action": "qldb:ListLedgers",
      "privesc": false,
      "resource_exposure": false
    },
    {
      "access_level": "Read",
      "action": "qldb:DescribeLedger",
      "condition": null,
      "credentials_exposure": false,
      "data_access": false,
      "effective_action": "qldb:DescribeLedger",
      "privesc": false,
      "resource_exposure": false
    },
    {
      "access_level": "Write",
      "action": "qldb:ExportJournalToS3",
      "condition": null,
      "credentials_exposure": false,
      "data_access": false,
      "effective_action": "qldb:ExportJournalToS3",
      "privesc": false,
      "resource_exposure": false
    },
    {
      "access_level": "List",
      "action": "qldb:ListJournalS3Exports",
      "condition": null,
      "credentials_exposure": false,
      "data_access": false,
      "effective_action": "qldb:ListJournalS3Exports",
      "privesc": false,
      "resource_exposure": false
    },
    {
      "access_level": "List",
      "action": "qldb:ListJournalS3ExportsForLedger",
      "condition": null,
      "credentials_exposure": false,
      "data_access": false,
      "effective_action": "qldb:ListJournalS3ExportsForLedger",
      "privesc": false,
      "resource_exposure": false
    },
    {
      "access_level": "Read",
      "action": "qldb:DescribeJournalS3Export",
      "condition": null,
      "credentials_exposure": false,
      "data_access": false,
      "effective_action": "qldb:DescribeJournalS3Export",
      "privesc": false,
      "resource_exposure": false
    },
    {
      "access_level": "Write",
      "action": "qldb:CancelJournalKinesisStream",
      "condition": null,
      "credentials_exposure": false,
      "data_access": false,
      "effective_action": "qldb:CancelJournalKinesisStream",
      "privesc": false,
      "resource_exposure": false
    },
    {
      "access_level": "Read",
      "action": "qldb:DescribeJournalKinesisStream",
      "condition": null,
      "credentials_exposure": false,
      "data_access": false,
      "effective_action": "qldb:DescribeJournalKinesisStream",
      "privesc": false,
      "resource_exposure": false
    },
    {
      "access_level": "List",
      "action": "qldb:ListJournalKinesisStreamsForLedger",
      "condition": null,
      "credentials_exposure": false,
      "data_access": false,
      "effective_action": "qldb:ListJournalKinesisStreamsForLedger",
      "privesc": false,
      "resource_exposure": false
    },
    {
      "access_level": "Write",
      "action": "qldb:StreamJournalToKinesis",
      "condition": null,
      "credentials_exposure": false,
      "data_access": false,
      "effective_action": "qldb:StreamJournalToKinesis",
      "privesc": false,
      "resource_exposure": false
    },
    {
      "access_level": "Read",
      "action": "qldb:GetBlock",
      "condition": null,
      "credentials_exposure": false,
      "data_access": true,
      "effective_action": "qldb:GetBlock",
      "privesc": false,
      "resource_exposure": false
    },
    {
      "access_level": "Read",
      "action": "qldb:GetDigest",
      "condition": null,
      "credentials_exposure": false,
      "data_access": false,
      "effective_action": "qldb:GetDigest",
      "privesc": false,
      "resource_exposure": false
    },
    {
      "access_level": "Read",
      "action": "qldb:GetRevision",
      "condition": null,
      "credentials_exposure": false,
      "data_access": false,
      "effective_action": "qldb:GetRevision",
      "privesc": false,
      "resource_exposure": false
    },
    {
      "access_level": "Tagging",
      "action": "qldb:TagResource",
      "condition": null,
      "credentials_exposure": false,
      "data_access": false,
      "effective_action": "qldb:TagResource",
      "privesc": false,
      "resource_exposure": false
    },
    {
      "access_level": "Tagging",
      "action": "qldb:UntagResource",
      "condition": null,
      "credentials_exposure": false,
      "data_access": false,
      "effective_action": "qldb:UntagResource",
      "privesc": false,
      "resource_exposure": false
    },
    {
      "access_level": "Read",
      "action": "qldb:ListTagsForResource",
      "condition": null,
      "credentials_exposure": false,
      "data_access": false,
      "effective_action": "qldb:ListTagsForResource",
      "privesc": false,
      "resource_exposure": false
    },
    {
      "access_level": "Write",
      "action": "qldb:SendCommand",
      "condition": null,
      "credentials_exposure": false,
      "data_access": false,
      "effective_action": "qldb:SendCommand",
      "privesc": false,
      "resource_exposure": false
    },
    {
      "access_level": "Write",
      "action": "qldb:ExecuteStatement",
      "condition": null,
      "credentials_exposure": false,
      "data_access": false,
      "effective_action": "qldb:ExecuteStatement",
      "privesc": false,
      "resource_exposure": false
    },
    {
      "access_level": "Write",
      "action": "qldb:ShowCatalog",
      "condition": null,
      "credentials_exposure": false,
      "data_access": false,
      "effective_action": "qldb:ShowCatalog",
      "privesc": false,
      "resource_exposure": false
    },
    {
      "access_level": "Write",
      "action": "qldb:InsertSampleData",
      "condition": null,
      "credentials_exposure": false,
      "data_access": false,
      "effective_action": "qldb:InsertSampleData",
      "privesc": false,
      "resource_exposure": false
    },
    {
      "access_level": "Write",
      "action": "qldb:PartiQLCreateTable",
      "condition": null,
      "credentials_exposure": false,
      "data_access": false,
      "effective_action": "qldb:PartiQLCreateTable",
      "privesc": false,
      "resource_exposure": false
    },
    {
      "access_level": "Write",
      "action": "qldb:PartiQLCreateIndex",
      "condition": null,
      "credentials_exposure": false,
      "data_access": false,
      "effective_action": "qldb:PartiQLCreateIndex",
      "privesc": false,
      "resource_exposure": false
    },
    {
      "access_level": "Write",
      "action": "qldb:PartiQLDropTable",
      "condition": null,
      "credentials_exposure": false,
      "data_access": false,
      "effective_action": "qldb:PartiQLDropTable",
      "privesc": false,
      "resource_exposure": false
    },
    {
      "access_level": "Write",
      "action": "qldb:PartiQLDropIndex",
      "condition": null,
      "credentials_exposure": false,
      "data_access": false,
      "effective_action": "qldb:PartiQLDropIndex",
      "privesc": false,
      "resource_exposure": false
    },
    {
      "access_level": "Write",
      "action": "qldb:PartiQLUndropTable",
      "condition": null,
      "credentials_exposure": false,
      "data_access": false,
      "effective_action": "qldb:PartiQLUndropTable",
      "privesc": false,
      "resource_exposure": false
    },
    {
      "access_level": "Write",
      "action": "qldb:PartiQLDelete",
      "condition": null,
      "credentials_exposure": false,
      "data_access": false,
      "effective_action": "qldb:PartiQLDelete",
      "privesc": false,
      "resource_exposure": false
    },
    {
      "access_level": "Write",
      "action": "qldb:PartiQLInsert",
      "condition": null,
      "credentials_exposure": false,
      "data_access": false,
      "effective_action": "qldb:PartiQLInsert",
      "privesc": false,
      "resource_exposure": false
    },
    {
      "access_level": "Write",
      "action": "qldb:PartiQLUpdate",
      "condition": null,
      "credentials_exposure": false,
      "data_access": false,
      "effective_action": "qldb:PartiQLUpdate",
      "privesc": false,
      "resource_exposure": false
    },
    {
      "access_level": "Read",
      "action": "qldb:PartiQLSelect",
      "condition": null,
      "credentials_exposure": false,
      "data_access": false,
      "effective_action": "qldb:PartiQLSelect",
      "privesc": false,
      "resource_exposure": false
    },
    {
      "access_level": "Read",
      "action": "qldb:PartiQLHistoryFunction",
      "condition": null,
      "credentials_exposure": false,
      "data_access": false,
      "effective_action": "qldb:PartiQLHistoryFunction",
      "privesc": false,
      "resource_exposure": false
    },
    {
      "access_level": "Write",
      "action": "qldb:PartiQLRedact",
      "condition": null,
      "credentials_exposure": false,
      "data_access": false,
      "effective_action": "qldb:PartiQLRedact",
      "privesc": false,
      "resource_exposure": false
    },
    {
      "access_level": "Write",
      "action": "dbqms:*",
      "condition": null,
      "credentials_exposure": false,
      "data_access": false,
      "effective_action": "dbqms:CreateFavoriteQuery",
      "privesc": false,
      "resource_exposure": false
    },
    {
      "access_level": "Write",
      "action": "dbqms:*",
      "condition": null,
      "credentials_exposure": false,
      "data_access": false,
      "effective_action": "dbqms:CreateQueryHistory",
      "privesc": false,
      "resource_exposure": false
    },
    {
      "access_level": "Write",
      "action": "dbqms:*",
      "condition": null,
      "credentials_exposure": false,
      "data_access": false,
      "effective_action": "dbqms:CreateTab",
      "privesc": false,
      "resource_exposure": false
    },
    {
      "access_level": "Write",
      "action": "dbqms:*",
      "condition": null,
      "credentials_exposure": false,
      "data_access": false,
      "effective_action": "dbqms:DeleteFavoriteQueries",
      "privesc": false,
      "resource_exposure": false
    },
    {
      "access_level": "Write",
      "action": "dbqms:*",
      "condition": null,
      "credentials_exposure": false,
      "data_access": false,
      "effective_action": "dbqms:DeleteQueryHistory",
      "privesc": false,
      "resource_exposure": false
    },
    {
      "access_level": "Write",
      "action": "dbqms:*",
      "condition": null,
      "credentials_exposure": false,
      "data_access": false,
      "effective_action": "dbqms:DeleteTab",
      "privesc": false,
      "resource_exposure": false
    },
    {
      "access_level": "List",
      "action": "dbqms:*",
      "condition": null,
      "credentials_exposure": false,
      "data_access": false,
      "effective_action": "dbqms:DescribeFavoriteQueries",
      "privesc": false,
      "resource_exposure": false
    },
    {
      "access_level": "List",
      "action": "dbqms:*",
      "condition": null,
      "credentials_exposure": false,
      "data_access": false,
      "effective_action": "dbqms:DescribeQueryHistory",
      "privesc": false,
      "resource_exposure": false
    },
    {
      "access_level": "List",
      "action": "dbqms:*",
      "condition": null,
      "credentials_exposure": false,
      "data_access": false,
      "effective_action": "dbqms:DescribeTabs",
      "privesc": false,
      "resource_exposure": false
    },
    {
      "access_level": "Read",
      "action": "dbqms:*",
      "condition": null,
      "credentials_exposure": false,
      "data_access": false,
      "effective_action": "dbqms:GetQueryString",
      "privesc": false,
      "resource_exposure": false
    },
    {
      "access_level": "Write",
      "action": "dbqms:*",
      "condition": null,
      "credentials_exposure": false,
      "data_access": false,
      "effective_action": "dbqms:UpdateFavoriteQuery",
      "privesc": false,
      "resource_exposure": false
    },
    {
      "access_level": "Write",
      "action": "dbqms:*",
      "condition": null,
      "credentials_exposure": false,
      "data_access": false,
      "effective_action": "dbqms:UpdateQueryHistory",
      "privesc": false,
      "resource_exposure": false
    },
    {
      "access_level": "Write",
      "action": "dbqms:*",
      "condition": null,
      "credentials_exposure": false,
      "data_access": false,
      "effective_action": "dbqms:UpdateTab",
      "privesc": false,
      "resource_exposure": false
    },
    {
      "access_level": "List",
      "action": "kinesis:ListStreams",
      "condition": null,
      "credentials_exposure": false,
      "data_access": false,
      "effective_action": "kinesis:ListStreams",
      "privesc": false,
      "resource_exposure": false
    },
    {
      "access_level": "Read",
      "action": "kinesis:DescribeStream",
      "condition": null,
      "credentials_exposure": false,
      "data_access": false,
      "effective_action": "kinesis:DescribeStream",
      "privesc": false,
      "resource_exposure": false
    },
    {
      "access_level": "Permissions management",
      "action": "iam:PassRole",
      "condition": {
        "StringEquals": {
          "iam:PassedToService": "qldb.amazonaws.com"
        }
      },
      "credentials_exposure": false,
      "data_access": false,
      "effective_action": "iam:PassRole",
      "privesc": true,
      "resource_exposure": true
    }
  ],
  "grantless": false,
  "malformed": false,
  "name": "AmazonQLDBConsoleFullAccess",
  "privesc": true,
  "resource_exposure": true,
  "undocumented_actions": false,
  "unknown_actions": [],
  "updatedate": "2022-11-04T17:01:10+00:00",
  "version": "v5"
}