{
  "access_levels": [
    "List",
    "Read"
  ],
  "arn": "arn:aws:iam::aws:policy/CloudWatchSyntheticsReadOnlyAccess",
  "createdate": "2020-03-06T19:26:01Z",
  "credentials_exposure": false,
  "data_access": false,
  "deprecated": false,
  "document": {
    "Statement": [
      {
        "Action": [
          "synthetics:Describe*",
          "synthetics:Get*",
          "synthetics:List*"
        ],
        "Effect": "Allow",
        "Resource": "*"
      }
    ],
    "Version": "2012-10-17"
  },
  "effective_actions": [
    {
      "access_level": "Read",
      "action": "synthetics:Describe*",
      "condition": null,
      "credentials_exposure": false,
      "data_access": false,
      "effective_action": "synthetics:DescribeCanaries",
      "privesc": false,
      "resource_exposure": false
    },
    {
      "access_level": "Read",
      "action": "synthetics:Describe*",
      "condition": null,
      "credentials_exposure": false,
      "data_access": false,
      "effective_action": "synthetics:DescribeCanariesLastRun",
      "privesc": false,
      "resource_exposure": false
    },
    {
      "access_level": "Read",
      "action": "synthetics:Describe*",
      "condition": null,
      "credentials_exposure": false,
      "data_access": false,
      "effective_action": "synthetics:DescribeRuntimeVersions",
      "privesc": false,
      "resource_exposure": false
    },
    {
      "access_level": "Read",
      "action": "synthetics:Get*",
      "condition": null,
      "credentials_exposure": false,
      "data_access": false,
      "effective_action": "synthetics:GetCanary",
      "privesc": false,
      "resource_exposure": false
    },
    {
      "access_level": "Read",
      "action": "synthetics:Get*",
      "condition": null,
      "credentials_exposure": false,
      "data_access": false,
      "effective_action": "synthetics:GetCanaryRuns",
      "privesc": false,
      "resource_exposure": false
    },
    {
      "access_level": "Read",
      "action": "synthetics:Get*",
      "condition": null,
      "credentials_exposure": false,
      "data_access": false,
      "effective_action": "synthetics:GetGroup",
      "privesc": false,
      "resource_exposure": false
    },
    {
      "access_level": "List",
      "action": "synthetics:List*",
      "condition": null,
      "credentials_exposure": false,
      "data_access": false,
      "effective_action": "synthetics:ListAssociatedGroups",
      "privesc": false,
      "resource_exposure": false
    },
    {
      "access_level": "List",
      "action": "synthetics:List*",
      "condition": null,
      "credentials_exposure": false,
      "data_access": false,
      "effective_action": "synthetics:ListGroupResources",
      "privesc": false,
      "resource_exposure": false
    },
    {
      "access_level": "List",
      "action": "synthetics:List*",
      "condition": null,
      "credentials_exposure": false,
      "data_access": false,
      "effective_action": "synthetics:ListGroups",
      "privesc": false,
      "resource_exposure": false
    },
    {
      "access_level": "Read",
      "action": "synthetics:List*",
      "condition": null,
      "credentials_exposure": false,
      "data_access": false,
      "effective_action": "synthetics:ListTagsForResource",
      "privesc": false,
      "resource_exposure": false
    }
  ],
  "malformed": false,
  "name": "CloudWatchSyntheticsReadOnlyAccess",
  "privesc": false,
  "resource_exposure": false,
  "undocumented_actions": false,
  "unknown_actions": [],
  "updatedate": "2020-03-06T19:26:01+00:00",
  "version": "v2"
}